.DS_Store
anvil/__init__.py
anvil/gen3_auth.py
anvil/__pycache__/__init__.cpython-37.pyc
anvil/clients/__init__.py
anvil/clients/fhir_client.py
anvil/clients/fhir_curl.py
anvil/clients/gen3_auth.py
anvil/clients/smart_auth.py
anvil/data/data_ingestion_tracker.json
anvil/dbgap/__init__.py
anvil/dbgap/api.py
anvil/etl/__init__.py
anvil/etl/anvil_etl.py
anvil/etl/cli.py
anvil/etl/extract.py
anvil/etl/load.py
anvil/etl/transform.py
anvil/etl/utility.py
anvil/etl/extractors/__init__.py
anvil/etl/extractors/data_ingestion_tracker.py
anvil/etl/extractors/gen3.py
anvil/etl/extractors/google.py
anvil/etl/extractors/terra.py
anvil/etl/loaders/__init__.py
anvil/etl/loaders/fhir/__init__.py
anvil/etl/loaders/fhir/dataset.py
anvil/etl/loaders/fhir/datastore.py
anvil/etl/loaders/fhir/implementation_guide.py
anvil/etl/loaders/fhir/initializer.py
anvil/etl/transformers/__init__.py
anvil/etl/transformers/fhir_writer.py
anvil/etl/transformers/normalizer.py
anvil/etl/transformers/normalizer_methods.py
anvil/etl/utilities/__init__.py
anvil/etl/utilities/bioontology_lookup.py
anvil/etl/utilities/config.yaml
anvil/etl/utilities/disease_normalizer.py
anvil/etl/utilities/entities.py
anvil/etl/utilities/shell_helper.py
anvil/fhir/__init__.py
anvil/fhir/client.py
anvil/fhir/smart_auth.py
anvil/gen3/__init__.py
anvil/gen3/drs_files.py
anvil/gen3/entities.py
anvil/terra/__init__.py
anvil/terra/api.py
anvil/terra/blob.py
anvil/terra/reconciler.py
anvil/terra/sample.py
anvil/terra/subject.py
anvil/terra/workspace.py
anvil/terra/workspace_graph.py
anvil/terra/__pycache__/__init__.cpython-37.pyc
anvil/terra/__pycache__/workspace.cpython-37.pyc
anvil/transformers/__init__.py
anvil/transformers/transformer.py
anvil/transformers/fhir/__init__.py
anvil/transformers/fhir/attachment.py
anvil/transformers/fhir/disease_normalizer.py
anvil/transformers/fhir/document_reference.py
anvil/transformers/fhir/observation.py
anvil/transformers/fhir/organization.py
anvil/transformers/fhir/patient.py
pyAnVIL-0.1.0.dist-info/METADATA
pyAnVIL-0.1.0.dist-info/WHEEL
pyAnVIL-0.1.0.dist-info/entry_points.txt
pyAnVIL-0.1.0.dist-info/top_level.txt
pyAnVIL-0.1.0.dist-info/RECORD
