Metadata-Version: 2.1
Name: pyAnVIL
Version: 0.1.0
Summary: AnVIL client library. Data harmonization, gen3, terra single sign-on use cases.
Home-page: https://github.com/anvilproject/client-apis/pyAnVIL
Author: The AnVIL project
Author-email: walsbr@ohsu.edu
License: UNKNOWN
Project-URL: Bug Reports, https://github.com/anvilproject/client-apis/issues
Project-URL: Source, https://github.com/anvilproject/client-apis/
Keywords: AnVIL terra gen3 bioinformatics fhir
Platform: UNKNOWN
Classifier: Development Status :: 4 - Beta
Classifier: Intended Audience :: Developers
Classifier: Topic :: Software Development :: Build Tools
Classifier: License :: OSI Approved :: MIT License
Classifier: Programming Language :: Python :: 3.9
Requires-Python: >=3.9, <4
Requires-Dist: gen3 (==4.2.0)
Requires-Dist: firecloud (==0.16.31)
Requires-Dist: xmltodict (==0.12.0)
Requires-Dist: click (==8.1.2)
Requires-Dist: click-loglevel (==0.4.0.post1)
Requires-Dist: attrdict (==2.0.1)
Requires-Dist: google-cloud-storage (==2.0.0)
Requires-Dist: fastavro (==1.2.0)
Requires-Dist: tabulate (~=0.8.9)
Requires-Dist: requests (~=2.27.1)
Requires-Dist: pandas (~=1.4.2)
Requires-Dist: numpy (~=1.22.3)
Requires-Dist: PyYAML (~=5.4.1)
Requires-Dist: setuptools (~=60.2.0)
Requires-Dist: importlib-metadata (~=4.11.3)
